{
	"$type": "app.bsky.labeler.defs#labelerViewDetailed",
	"uri": "at://did:plc:2vncz5wfiypq5qdrujdvvft3/app.bsky.labeler.service/self",
	"cid": "bafyreicbtlobwew6pxnfcqo5zuy5apsyt2zoqolrchvq7vqxth2wjor4o4",
	"creator": {
		"did": "did:plc:2vncz5wfiypq5qdrujdvvft3",
		"handle": "labels.midnightdoggo19.com",
		"displayName": "Republic of Labels",
		"avatar": "https://cdn.bsky.app/img/avatar/plain/did:plc:2vncz5wfiypq5qdrujdvvft3/bafkreicxridbcfnl4lhqmxowg6rza7iqqkwloxzy32vh43ymwhkno7hhs4@jpeg",
		"associated": {
			"labeler": true
		},
		"labels": [],
		"createdAt": "2024-12-14T10:07:33.244Z",
		"indexedAt": "2024-12-14T11:13:58.644Z"
	},
	"likeCount": 2,
	"indexedAt": "2024-12-14T19:29:32.755Z",
	"labels": [],
	"policies": {
		"labelValueDefinitions": [
			{
				"adultOnly": true,
				"blurs": "none",
				"defaultSetting": "warn",
				"identifier": "elder",
				"locales": [
					{
						"description": "Warning: Bluesky Elder",
						"lang": "en",
						"name": "Bluesky Elder"
					}
				],
				"severity": "alert"
			}
		],
		"labelValues": [
			"dmca-violation",
			"elder"
		]
	}
}