{
	"$type": "app.bsky.labeler.defs#labelerViewDetailed",
	"uri": "at://did:plc:3pyykdccdni5mdw2kgd465fw/app.bsky.labeler.service/self",
	"cid": "bafyreidutsjeqb4zxqwz7psid7uwcmqhk7qa74arej7uufwz3ryk2ridci",
	"creator": {
		"did": "did:plc:3pyykdccdni5mdw2kgd465fw",
		"handle": "bigkidnow.bsky.social",
		"displayName": "",
		"avatar": "https://cdn.bsky.app/img/avatar/plain/did:plc:3pyykdccdni5mdw2kgd465fw/bafkreidp7xuscnbfmmb2ddjl26ko7d3irlnafpzubtzggiqfvsrdw4ctxy@jpeg",
		"associated": {
			"labeler": true,
			"chat": {
				"allowIncoming": "none"
			}
		},
		"labels": [
			{
				"src": "did:plc:3pyykdccdni5mdw2kgd465fw",
				"uri": "at://did:plc:3pyykdccdni5mdw2kgd465fw/app.bsky.actor.profile/self",
				"cid": "bafyreieqdbfpk4ujes4mshbxtcul635uqahmi6usw6kmhztfwq7ujvuqoy",
				"val": "!no-unauthenticated",
				"cts": "2024-11-14T22:26:35.453Z"
			}
		],
		"createdAt": "2024-11-14T22:26:36.534Z",
		"indexedAt": "2024-11-15T01:10:29.451Z"
	},
	"likeCount": 1,
	"indexedAt": "2024-11-15T01:21:58.864Z",
	"labels": [],
	"policies": {
		"labelValueDefinitions": [
			{
				"adultOnly": false,
				"blurs": "none",
				"defaultSetting": "warn",
				"identifier": "adultsonly",
				"locales": [
					{
						"description": "This account contains content which is not safe for minor audiences. Viewer discretion is advised.",
						"lang": "en",
						"name": "18+"
					}
				],
				"severity": "inform"
			}
		],
		"labelValues": [
			"adultsonly"
		]
	}
}