{
	"$type": "app.bsky.labeler.defs#labelerViewDetailed",
	"uri": "at://did:plc:r55ow3tocux5kafs5dq445fy/app.bsky.labeler.service/self",
	"cid": "bafyreibrn574qa3lv7smou7wazpsm3fkuqbo2rbtn2lq4mt5wgv2k366ua",
	"creator": {
		"did": "did:plc:r55ow3tocux5kafs5dq445fy",
		"handle": "moderation-de.bsky.app",
		"displayName": "Bluesky Moderation Service (Germany)",
		"associated": {
			"labeler": true
		},
		"labels": [],
		"createdAt": "2024-09-30T21:46:20.810Z",
		"description": "Offizieller Bluesky-Moderationsdienst. https://bsky.social/about/support/community-guidelines",
		"indexedAt": "2024-09-30T21:47:04.010Z"
	},
	"likeCount": 0,
	"indexedAt": "2024-10-10T16:58:45.868Z",
	"labels": [],
	"policies": {
		"labelValues": []
	}
}