{
	"$type": "app.bsky.labeler.defs#labelerViewDetailed",
	"uri": "at://did:plc:vqtx3z2moqa3pp7hjehxgdht/app.bsky.labeler.service/self",
	"cid": "bafyreih4jnnbnp2qwopqgx3fccf5c6zoeaugp57qrew73hgkihdcoz3dnm",
	"creator": {
		"did": "did:plc:vqtx3z2moqa3pp7hjehxgdht",
		"handle": "furrycreatorlabels.bsky.social",
		"displayName": "",
		"avatar": "https://cdn.bsky.app/img/avatar/plain/did:plc:vqtx3z2moqa3pp7hjehxgdht/bafkreiehysdchpn55yh6wqiyudwwrqzr43o6e3ulkqrcv6lqn3yteinwka@jpeg",
		"associated": {
			"labeler": true
		},
		"labels": [],
		"createdAt": "2024-10-20T21:23:27.008Z",
		"description": "currently testing. just ignore this for now please",
		"indexedAt": "2024-10-20T22:47:43.709Z"
	},
	"likeCount": 1,
	"indexedAt": "2024-10-20T22:21:41.914Z",
	"labels": [],
	"policies": {
		"labelValueDefinitions": [
			{
				"adultOnly": false,
				"blurs": "none",
				"defaultSetting": "ignore",
				"identifier": "artist",
				"locales": [
					{
						"description": "This creator is an artist!",
						"lang": "en",
						"name": "Artist"
					}
				],
				"severity": "inform"
			},
			{
				"adultOnly": false,
				"blurs": "none",
				"defaultSetting": "ignore",
				"identifier": "writer",
				"locales": [
					{
						"description": "This creator is a writer!",
						"lang": "en",
						"name": "Writer"
					}
				],
				"severity": "inform"
			},
			{
				"adultOnly": false,
				"blurs": "none",
				"defaultSetting": "ignore",
				"identifier": "Sound Engineer",
				"locales": [
					{
						"description": "This creator is a sound engineer!",
						"lang": "en",
						"name": "Sound Engineer"
					}
				],
				"severity": "inform"
			}
		],
		"labelValues": [
			"artist",
			"writer",
			"Sound Engineer"
		]
	}
}